__init__.py
code_generator.py
entity_generator.py
modelgen-0.2.2.dist-info/METADATA
modelgen-0.2.2.dist-info/WHEEL
modelgen-0.2.2.dist-info/top_level.txt
modelgen-0.2.2.dist-info/RECORD
