Metadata-Version: 2.4
Name: modelgen
Version: 0.2.2
Summary: Add your description here
Requires-Python: >=3.12
Requires-Dist: datamodel-code-generator>=0.33.0
Requires-Dist: jinja2>=3.1.6
Requires-Dist: pyyaml>=6.0.2
Requires-Dist: sqlalchemy>=2.0.43
Requires-Dist: sqlglot[rs]>=27.14.0
